durable/__init__.py
durable_execution-0.0.0.dist-info/METADATA
durable_execution-0.0.0.dist-info/WHEEL
durable_execution-0.0.0.dist-info/top_level.txt
durable_execution-0.0.0.dist-info/RECORD
