Metadata-Version: 2.2
Name: durable-execution
Version: 0.0.0
Summary: Coming soon
Author-email: Wiktor Tomczak <wiktor.tomczak@gmail.com>
